pypiper/__init__.py
pypiper/_version.py
pypiper/const.py
pypiper/exceptions.py
pypiper/flags.py
pypiper/folder_context.py
pypiper/manager.py
pypiper/ngstk.py
pypiper/pipeline.py
pypiper/stage.py
pypiper/utils.py
piper-0.14.4.dist-info/LICENSE.txt
piper-0.14.4.dist-info/METADATA
piper-0.14.4.dist-info/WHEEL
piper-0.14.4.dist-info/top_level.txt
piper-0.14.4.dist-info/RECORD
